{"2024":{"gennaio":{"29 gennaio 2024 alle ore 21:29:31":{"building":"Hostage","description":"Lavoro fatto 1","workedHours":"2"},"31 gennaio 2024 alle ore 20:36:59":{"building":"Hostage","description":"Lavoro fatto 1","workedHours":"2"}}},"lambeosaurus":{"dimensions":{"height":2.1,"length":12.5,"weight":5000}},"rapportino-service":{"gennaio":{"19 gennaio 2024 alle ore 18:28:44":{"building":"Hostage","description":"Lavoro fatto 1","workedHours":"2"},"19 gennaio 2024 alle ore 18:33:45":{"building":"Hostage","description":"Lavoro fatto 1","workedHours":"2"}}},"stegosaurus":{"dimensions":{"height":4,"length":9,"weight":2500}},"zucca":{"gennaio":{"31 gennaio 2024 alle ore 20:38:22":{"building":"Hostage","description":"Lavoro fatto 1","workedHours":"2"}}},"zucca@gmailcom":{"gennaio":{"31 gennaio 2024 alle ore 21:05:26":{"building":"Hostage","description":"Lavoro fatto 1","workedHours":"2"}}}}